{"examples_aws-setup.md":"DdsvhJPs","examples_ci-cd.md":"CKzIuts7","examples_index.md":"DImIjeSk","examples_laravel.md":"B4lXUCJu","examples_multi-environment.md":"BoCqsuS3","guide_configuration.md":"CqQV1Tyc","guide_contexts.md":"p4q8klbi","guide_index.md":"BOp2BqZ0","guide_installation.md":"DhieCrA2","guide_quick-start.md":"Bh7hgexP","guide_stages.md":"CRiqpvY2","guide_templates.md":"8AkKHUMd","guide_vaults.md":"CHejhwDa","guide_vaults_aws-secrets-manager.md":"DaNgyDla","guide_vaults_aws-ssm.md":"B6oAg0A_","guide_vaults_local.md":"4HDL_B2s","index.md":"Ctjy2GqU","reference_commands_cache.md":"KVSbOYZZ","reference_commands_configure.md":"9xN2doQU","reference_commands_copy.md":"7-BsrnNY","reference_commands_delete.md":"psCuA5XV","reference_commands_diff.md":"CC81GpGh","reference_commands_export.md":"1sSWSWs0","reference_commands_get.md":"Bo-oe3pX","reference_commands_import.md":"D2JXKcsi","reference_commands_info.md":"De6hmeB_","reference_commands_list.md":"DqAKeCjy","reference_commands_merge.md":"pH8yZemm","reference_commands_set.md":"C_0OmQ0P","reference_commands_vault-add.md":"DpT9iDvN","reference_commands_vault-list.md":"D8xOMMPE","reference_index.md":"XqJM8q0y"}
